[
  {
    "type": "project",
    "company": "Cowin Clone",
    "position": "MERN Stack, SMS APIs",
    "duration": "Jan 2022",
    "github": "https://github.com/lusifer2644A/cowin_clone",
    "website": "https://cowin-clone1.herokuapp.com/",
    "data": []
  },
  {
    "type": "project",
    "company": "Devbook",
    "position": "MERN Stack, HTML, CSS, Github APIs.",
    "duration": "Aug 2021 - Sep 2021",
    "github": "https://github.com/lusifer2644A/DevBook",
    "website": "https://projectdevbook.herokuapp.com/",
    "data": []
  },
  {
    "type": "project",
    "company": "Sorting Visualiser",
    "position": "React.js, HTML, CSS, JavaScript",
    "duration": "June 2021",
    "github": "https://github.com/lusifer2644A/Sorting-Visualizer",
    "website": "https://sorting-vizualizer.netlify.app/",
    "data": []
  }
]
